modelgauge/annotators/llama_guard_annotator.py
modelgauge/suts/together_cli.py
modelgauge/suts/together_client.py
modelgauge_together-0.5.1.dist-info/METADATA
modelgauge_together-0.5.1.dist-info/WHEEL
modelgauge_together-0.5.1.dist-info/RECORD
