Metadata-Version: 2.1
Name: modelgauge-together
Version: 0.5.1
Summary: 
Author: MLCommons AI Safety
Author-email: ai-safety-engineering@mlcommons.org
Requires-Python: >=3.10,<4.0
Classifier: Programming Language :: Python :: 3
Classifier: Programming Language :: Python :: 3.10
Classifier: Programming Language :: Python :: 3.11
Classifier: Programming Language :: Python :: 3.12
Requires-Dist: together (>=0.2.11,<0.3.0)
Requires-Dist: types-requests (>=2.31.0.20240125,<3.0.0.0)
